whatlangid/__init__.py
whatlangid/exceptions.py
whatlangid/predict_lang.py
whatlangid/use_bin.py
whatlangid/model/lid.176.ftz
whatlangid-1.0.11.dist-info/LICENSE
whatlangid-1.0.11.dist-info/METADATA
whatlangid-1.0.11.dist-info/WHEEL
whatlangid-1.0.11.dist-info/top_level.txt
whatlangid-1.0.11.dist-info/RECORD
