Metadata-Version: 2.1
Name: whatlangid
Version: 1.0.11
Summary: Lightning Fast Language Prediction powered by FastText and langid.
Home-page: https://github.com/bung87/whatlangid
Author: bung87
License: Apache License, Version 2.0
Keywords: language detection library
Platform: UNKNOWN
Classifier: Development Status :: 5 - Production/Stable
Classifier: Intended Audience :: Developers
Classifier: License :: OSI Approved :: Apache Software License
Classifier: Operating System :: OS Independent
Classifier: Programming Language :: Python :: 3
Classifier: Programming Language :: Python :: 3.2
Classifier: Programming Language :: Python :: 3.4
Classifier: Programming Language :: Python :: 3.5
Classifier: Programming Language :: Python :: 3.6
Requires-Python: >=3
Requires-Dist: fasttext (>=0.9.1)
Requires-Dist: langid (>=1.1.6)
Requires-Dist: tqdm (>=4.23.3)
Requires-Dist: requests (>=2.18.4)
